datachallenge/scripts/format_metrics.py
datachallenge/scripts/wrap_yaml.py
ocb_dc_ose_2021/__init__.py
ocb_dc_ose_2021/mods/__init__.py
ocb_dc_ose_2021/mods/cmems_get.py
ocb_dc_ose_2021/mods/interp_on_track.py
ocb_dc_ose_2021/mods/lambdax.py
ocb_dc_ose_2021/mods/mu.py
ocb_dc_ose_2021/mods/prepare_track.py
ocb_dc_ose_2021/pipelines/__init__.py
ocb_dc_ose_2021/pipelines/input_data.py
ocb_dc_ose_2021/pipelines/metrics.py
ocb_dc_ose_2021-2024.4.8.1714.dist-info/LICENSE
ocb_dc_ose_2021-2024.4.8.1714.dist-info/METADATA
ocb_dc_ose_2021-2024.4.8.1714.dist-info/WHEEL
ocb_dc_ose_2021-2024.4.8.1714.dist-info/entry_points.txt
ocb_dc_ose_2021-2024.4.8.1714.dist-info/top_level.txt
ocb_dc_ose_2021-2024.4.8.1714.dist-info/RECORD
