Metadata-Version: 2.1
Name: ocb-dc-ose-2021
Version: 2024.4.8.1714
Author-email: Quentin Febvre <quentin.febvre@gmail.com>
Project-URL: Repository, https://github.com/quentinf00/ocb-dc-ose-2021.git
License-File: LICENSE
Requires-Dist: aprl
Requires-Dist: copernicusmarine
